jupyterlab_gcloud_auth/__init__.py
jupyterlab_gcloud_auth/gcloud_auth_helper.py
jupyterlab_gcloud_auth-0.2.4.data/data/etc/jupyter/jupyter_notebook_config.d/jupyterlab_gcloud_auth.json
jupyterlab_gcloud_auth-0.2.4.dist-info/LICENSE
jupyterlab_gcloud_auth-0.2.4.dist-info/METADATA
jupyterlab_gcloud_auth-0.2.4.dist-info/WHEEL
jupyterlab_gcloud_auth-0.2.4.dist-info/top_level.txt
jupyterlab_gcloud_auth-0.2.4.dist-info/RECORD
