Metadata-Version: 2.1
Name: jupyterlab-gcloud-auth
Version: 0.2.4
Summary: Plugin that allows to run gclout auth directly from the Notebooks.
Home-page: UNKNOWN
Author: Viacheslav Kovalevskyi
Author-email: viacheslav@kovalevskyi.com
License: MIT
Keywords: Jupyter,JupyterLab,GitHub,GCP
Platform: Linux
Platform: Mac OS X
Platform: Windows
Classifier: Intended Audience :: Developers
Classifier: Intended Audience :: System Administrators
Classifier: Intended Audience :: Science/Research
Classifier: License :: OSI Approved :: MIT License
Classifier: Programming Language :: Python
Classifier: Programming Language :: Python :: 3
Requires-Python: >=3.5
